freva_deployment/__init__.py
freva_deployment/__main__.py
freva_deployment/deploy.py
freva_deployment/error.py
freva_deployment/keys.py
freva_deployment/logger.py
freva_deployment/py.typed
freva_deployment/runner.py
freva_deployment/utils.py
freva_deployment/versions.json
freva_deployment/versions.py
freva_deployment/callback_plugins/__init__.py
freva_deployment/callback_plugins/deployment_plugin.py
freva_deployment/cli/__init__.py
freva_deployment/cli/_compose.py
freva_deployment/cli/_config.py
freva_deployment/cli/_deploy.py
freva_deployment/cli/_kubernets.py
freva_deployment/cli/_migrate.py
freva_deployment/ui/__init__.py
freva_deployment/ui/deployment_tui/__init__.py
freva_deployment/ui/deployment_tui/base.py
freva_deployment/ui/deployment_tui/deploy_forms.py
freva_deployment/ui/deployment_tui/main_window.py
freva_deployment-2601.0.0.data/data/share/freva/deployment/config/conda-environment.yml
freva_deployment-2601.0.0.data/data/share/freva/deployment/config/create_tables.sql
freva_deployment-2601.0.0.data/data/share/freva/deployment/config/evaluation_system.conf.tmpl
freva_deployment-2601.0.0.data/data/share/freva/deployment/config/inventory.toml
freva_deployment-2601.0.0.data/data/share/freva/deployment/config/unprivileged-user.toml
freva_deployment-2601.0.0.data/data/share/freva/deployment/k8s-deployment/templates/00-namespace.yaml.j2
freva_deployment-2601.0.0.data/data/share/freva/deployment/k8s-deployment/templates/01-secrets.yaml.j2
freva_deployment-2601.0.0.data/data/share/freva/deployment/k8s-deployment/templates/02-pvcs.yaml.j2
freva_deployment-2601.0.0.data/data/share/freva/deployment/k8s-deployment/templates/10-mysql.yaml.j2
freva_deployment-2601.0.0.data/data/share/freva/deployment/k8s-deployment/templates/11-redis.yaml.j2
freva_deployment-2601.0.0.data/data/share/freva/deployment/k8s-deployment/templates/12-solr.yaml.j2
freva_deployment-2601.0.0.data/data/share/freva/deployment/k8s-deployment/templates/13-vault.yaml.j2
freva_deployment-2601.0.0.dist-info/entry_points.txt
freva_deployment-2601.0.0.dist-info/licenses/LICENSE
freva_deployment-2601.0.0.dist-info/WHEEL
freva_deployment-2601.0.0.dist-info/METADATA
freva_deployment-2601.0.0.dist-info/RECORD
