Metadata-Version: 2.4
Name: freva-deployment
Version: 2601.0.0
Summary: Deployment of the Free Evaluation Framework Freva
Author-email: "DKRZ, Clint" <freva@dkrz.de>
Requires-Python: >=3.8
Classifier: Development Status :: 3 - Alpha
Classifier: Environment :: Console
Classifier: Intended Audience :: Developers
Classifier: Intended Audience :: Science/Research
Classifier: License :: OSI Approved :: BSD License
Classifier: Operating System :: POSIX :: Linux
Classifier: Programming Language :: Python :: 3
License-File: LICENSE
Requires-Dist: appdirs
Requires-Dist: ansible
Requires-Dist: ansible-core
Requires-Dist: namegenerator
Requires-Dist: cowsay
Requires-Dist: npyscreen
Requires-Dist: paramiko
Requires-Dist: packaging
Requires-Dist: PyMySQL
Requires-Dist: PyYAML
Requires-Dist: rich
Requires-Dist: rich-argparse
Requires-Dist: toml
Requires-Dist: tomlkit
Requires-Dist: typing_extensions
Requires-Dist: requests
Requires-Dist: flit ; extra == "dev"
Requires-Dist: tox ; extra == "dev"
Requires-Dist: kubernetes ; extra == "dev"
Requires-Dist: pydata-sphinx-theme ; extra == "doc"
Requires-Dist: sphinx ; extra == "doc"
Requires-Dist: sphinx-copybutton ; extra == "doc"
Requires-Dist: sphinxext-opengraph ; extra == "doc"
Requires-Dist: recommonmark ; extra == "doc"
Requires-Dist: linkify ; extra == "doc"
Requires-Dist: linkify-it-py ; extra == "doc"
Requires-Dist: sphinx_sitemap ; extra == "doc"
Requires-Dist: sphinx_favicon ; extra == "doc"
Requires-Dist: sphinx_togglebutton ; extra == "doc"
Requires-Dist: myst-parser ; extra == "doc"
Requires-Dist: sphinx-design ; extra == "doc"
Requires-Dist: sphinx-execute-code-python3 ; extra == "doc"
Requires-Dist: kubernetes ; extra == "k8s"
Requires-Dist: cryptography ; extra == "unix"
Requires-Dist: pyinstaller ; extra == "unix"
Requires-Dist: mock ; extra == "unix"
Requires-Dist: cryptography ; extra == "win"
Requires-Dist: windows-curses ; extra == "win"
Requires-Dist: pyinstaller ; extra == "win"
Requires-Dist: mock ; extra == "win"
Requires-Dist: pywin32 ; extra == "win"
Project-URL: Documentation, https://github.com/freva-org/freva-admin
Project-URL: Home, https://github.com/freva-org/freva-admin
Project-URL: Issues, https://github.com/freva-org/freva-admin/issues
Project-URL: Source, https://github.com/freva-org/freva-admin
Provides-Extra: dev
Provides-Extra: doc
Provides-Extra: k8s
Provides-Extra: unix
Provides-Extra: win
